zoopla/__init__.py
zoopla/__version__.py
zoopla/api.py
zoopla/enums.py
zoopla/exceptions.py
zoopla/fields.py
zoopla/schemas.py
zoopla-1.0.0.dist-info/METADATA
zoopla-1.0.0.dist-info/WHEEL
zoopla-1.0.0.dist-info/top_level.txt
zoopla-1.0.0.dist-info/RECORD
