Metadata-Version: 2.1
Name: zoopla
Version: 1.0.0
Summary: A Python wrapper for the Zoopla API
Home-page: https://github.com/anthonybloomer/zoopla
Author: Anthony Bloomer, Gabriele Alese
Author-email: ant0@protonmail.ch, gabriele@alese.it
License: MIT
Keywords: zoopla,api
Platform: UNKNOWN
Classifier: Intended Audience :: Developers
Classifier: License :: OSI Approved :: MIT License
Classifier: Topic :: Software Development :: Libraries
Classifier: Programming Language :: Python :: 2.7
Classifier: Programming Language :: Python :: 3.6
Requires-Dist: marshmallow (<3,>=2.13.6)
Requires-Dist: requests (<3,>=2.11.1)
Requires-Dist: enum34 (<2,>=1.1.6)
